prettymd/__init__.py
prettymd/__main__.py
prettymd/formatter.py
prettymd-0.1.111.dist-info/LICENSE
prettymd-0.1.111.dist-info/METADATA
prettymd-0.1.111.dist-info/WHEEL
prettymd-0.1.111.dist-info/top_level.txt
prettymd-0.1.111.dist-info/RECORD
