Metadata-Version: 2.1
Name: prettymd
Version: 0.1.111
Summary: A tool that formats markdown text in Chinese.
Home-page: https://github.com/kingronjan/prettymd
Author: kingron
Author-email: kingronjan@qq.com
Keywords: prettymd
Classifier: Development Status :: 2 - Pre-Alpha
Classifier: Intended Audience :: Developers
Classifier: Natural Language :: English
Classifier: Programming Language :: Python :: 3
Classifier: Programming Language :: Python :: 3.5
Classifier: Programming Language :: Python :: 3.6
Classifier: Programming Language :: Python :: 3.7
Classifier: Programming Language :: Python :: 3.8
Requires-Python: >=3.5
License-File: LICENSE
